projdump2md/__init__.py
projdump2md/cli.py
projdump2md/version.py
projdump2md-0.1.0.dist-info/licenses/LICENSE
projdump2md-0.1.0.dist-info/METADATA
projdump2md-0.1.0.dist-info/WHEEL
projdump2md-0.1.0.dist-info/entry_points.txt
projdump2md-0.1.0.dist-info/top_level.txt
projdump2md-0.1.0.dist-info/RECORD
