Metadata-Version: 2.4
Name: projdump2md
Version: 0.1.0
Summary: Dump project files into a single markdown file with folder structure
Author-email: Jabez Winston <jabezwinston@gmail.com>
License-Expression: MIT
Project-URL: Homepage, https://github.com/jabezwinston/projdump2md
Project-URL: Repository, https://github.com/jabezwinston/projdump2md
Project-URL: Bug Tracker, https://github.com/jabezwinston/projdump2md/issues
Keywords: documentation,markdown,project,dump,files
Classifier: Development Status :: 4 - Beta
Classifier: Intended Audience :: Developers
Classifier: Operating System :: OS Independent
Classifier: Programming Language :: Python :: 3
Classifier: Topic :: Software Development :: Documentation
Classifier: Topic :: Utilities
Requires-Python: >=3.7
License-File: LICENSE
Dynamic: license-file
